{
  "total": 142946,
  "statuses": {
    "closed": 95379,
    "open": 47567
  },
  "reclassified": 54127,
  "not_reclassified": 88819,
  "human_waste_total": 2312,
  "encampment_total": 9282,
  "with_photo": 74876,
  "tags": {
    "Miscellaneous": 7143,
    "BPD: Quality of Life": 5739,
    "Wires: Downed/Low Hanging": 4062,
    "BPD: Traffic/Parking": 3366,
    "Unsheltered Persons": 3106,
    "Animal Care & Control": 2304,
    "Human Waste": 2277,
    "USPS: Graffiti/Mailbox Issues": 2144,
    "Mass DCR": 2119,
    "MBTA": 1967,
    "Encampments": 1635,
    "BPD: Crime": 1556,
    "ONS Coordinator Issues": 1528,
    "Homeless Issues": 1498,
    "Mass DOT": 1142,
    "National Grid": 1128,
    "Shopping Carts": 1009,
    "Fire Department Issues": 946,
    "Eversource/Power Outage": 787,
    "BHA Issues": 727,
    "Cable/Telephone/Broadband Issues": 686,
    "Noise Pollution": 597,
    "BPD: Administrative Issues": 502,
    "Elderly Concerns": 495,
    "City-owned Lots/Properties": 407,
    "School Administration": 393,
    "Senior Home Repair": 369,
    "Boston Center for Youth and Families": 362,
    "School Maintenance": 345,
    "Air Pollution": 305,
    "Licensing": 282,
    "Mayor's Scheduling": 268,
    "Department of Neighborhood Development": 264,
    "JC Decaux (WALL Furniture)": 232,
    "Library Issues": 194,
    "Grass Cutting": 172,
    "Outdoor Dining": 164,
    "Steam Leaks": 138,
    "Mayor's Request": 121,
    "Consumer Affairs": 120,
    "Ground Maintenance General": 116,
    "Immigrant Issues": 110,
    "Elections and Voting": 107,
    "Disabilities Issues": 92,
    "Electrical Safety": 82,
    "BRA Issues": 80,
    "Arts and Culture": 79,
    "Mayor's Information (Correspondence)": 73,
    "Aircraft Noise/Massport": 72,
    "Tourism, Sports, and Entertainment": 58,
    "Ball fields": 45,
    "EMS: Emergency Respose": 39,
    "Cleaning/Trash": 38,
    "Assessing": 37,
    "Trades General": 37,
    "Powerwash": 32,
    "Needles/Syringes": 30,
    "Landmarks Commission Issues": 30,
    "Snow/Ice": 23,
    "Municipal Protective Services Issues": 20,
    "AlertBoston": 20,
    "Bag Removal values (Clean-Up)": 19,
    "Arnold Arboretum": 18,
    "Boston Home Center": 18,
    "Litter/Glass": 18,
    "Payphones": 17,
    "Irrigation": 17,
    "Fence Repair": 17,
    "Youth Employment/Services": 15,
    "Law Department Issues": 12,
    "Play Equipment": 11,
    "Health Benefits/Insurance Issues": 11,
    "Food Trucks": 11,
    "Drinking Fountains": 10,
    "Claims vs City (City Clerk)": 10,
    "Barrel": 9,
    "Births/Marriages/Deaths Records": 9,
    "Mayor's Praise": 7,
    "Green Infratructure: Structures": 7,
    "Signage": 7,
    "Excise Tax": 6,
    "Fibar/Sand": 5,
    "Idling Vehicles": 4,
    "Ornamental Fountains": 4,
    "Graffiti": 4,
    "Flags": 3,
    "Street Furniture": 3,
    "Horticulture General": 3,
    "Taxi Cab Issues": 3,
    "Workers' Compensation": 3,
    "Senior Shuttle": 3,
    "Green Infrastructure: Vegetation": 3,
    "Green Infrastructure: Drainage": 3,
    "Public": 2,
    "Basketball Nets": 2,
    "Renew Boston": 2,
    "Fire Department Issues | Case (SR) Type: [Fire Department Issues": 2,
    "Benches": 1,
    "Senior home repair": 1,
    "Goal Post/Soccer Nets": 1,
    "City Hall To Go": 1,
    "BPD Districts": 1,
    "Support Services General": 1,
    "Encampments | Case (SR) Type: [Encampments": 1,
    "Unsheltered Persons | Case (SR) Type: [Unsheltered Persons": 1,
    "Homeless Issues | Case (SR) Type: [Unsheltered Persons": 1,
    "Neat Street Program": 1
  },
  "monthly": {
    "2023-01": 2916,
    "2023-02": 2754,
    "2023-03": 2802,
    "2023-04": 3078,
    "2023-05": 3780,
    "2023-06": 4073,
    "2023-07": 4848,
    "2023-08": 5205,
    "2023-09": 5159,
    "2023-10": 7512,
    "2023-11": 3319,
    "2023-12": 3390,
    "2024-01": 3985,
    "2024-02": 2802,
    "2024-03": 3025,
    "2024-04": 3515,
    "2024-05": 4415,
    "2024-06": 4164,
    "2024-07": 4423,
    "2024-08": 4479,
    "2024-09": 4189,
    "2024-10": 4145,
    "2024-11": 3119,
    "2024-12": 3006,
    "2025-01": 2783,
    "2025-02": 3488,
    "2025-03": 3225,
    "2025-04": 2927,
    "2025-05": 3731,
    "2025-06": 3782,
    "2025-07": 4256,
    "2025-08": 4365,
    "2025-09": 3755,
    "2025-10": 3168,
    "2025-11": 2278,
    "2025-12": 2205,
    "2026-01": 2719,
    "2026-02": 2825,
    "2026-03": 2759,
    "2026-04": 577
  },
  "waste_monthly": {
    "2023-01": 40,
    "2023-02": 26,
    "2023-03": 27,
    "2023-04": 27,
    "2023-05": 45,
    "2023-06": 50,
    "2023-07": 65,
    "2023-08": 76,
    "2023-09": 88,
    "2023-10": 65,
    "2023-11": 41,
    "2023-12": 29,
    "2024-01": 40,
    "2024-02": 37,
    "2024-03": 47,
    "2024-04": 38,
    "2024-05": 59,
    "2024-06": 75,
    "2024-07": 122,
    "2024-08": 142,
    "2024-09": 143,
    "2024-10": 102,
    "2024-11": 58,
    "2024-12": 57,
    "2025-01": 42,
    "2025-02": 35,
    "2025-03": 44,
    "2025-04": 52,
    "2025-05": 75,
    "2025-06": 78,
    "2025-07": 93,
    "2025-08": 104,
    "2025-09": 79,
    "2025-10": 83,
    "2025-11": 34,
    "2025-12": 19,
    "2026-01": 33,
    "2026-02": 9,
    "2026-03": 26,
    "2026-04": 7
  }
}